{
  "id": "character-film-e-t",
  "label": "E.T.",
  "subcategory": "film-characters",
  "franchise": "E.T.",
  "fandom_wiki": "ettheextraterrestrial",
  "requested_page": "E.T.",
  "recognisability": "high",
  "enabled": true,
  "approved": true,
  "notes": "",
  "status": "downloaded",
  "error": "",
  "local_path": "C:/Users/Lukeo/OneDrive/Desktop/website project/mrsmith/assets/images/clue-items/characters/film-characters/character-film-e-t.webp",
  "resolved_page": "E.T.",
  "display_title": "E.T.",
  "source_page": "https://ettheextraterrestrial.fandom.com/wiki/E.T.",
  "image_url": "https://static.wikia.nocookie.net/ettheextraterrestrial/images/6/6f/Thumb-ET.jpg/revision/latest?cb=20220814150338",
  "image_file": "File:Thumb-ET.jpg",
  "resolution_method": "portable-infobox",
  "original_width": 400,
  "original_height": 400,
  "saved_width": 400,
  "saved_height": 400,
  "bytes": 37902,
  "content_type": "image/webp"
}